hidiffusion/__init__.py
hidiffusion/hidiffusion.py
hidiffusion/utils.py
hidiffusion/sd_module_key/sd15_module_key.txt
hidiffusion/sd_module_key/sdxl_module_key.txt
hidiffusion-0.1.10.dist-info/LICENSE
hidiffusion-0.1.10.dist-info/METADATA
hidiffusion-0.1.10.dist-info/WHEEL
hidiffusion-0.1.10.dist-info/top_level.txt
hidiffusion-0.1.10.dist-info/RECORD
