Metadata-Version: 2.1
Name: hidiffusion
Version: 0.1.10
Summary: HiDiffusion: A training-free method to increase the resolution and speed of diffusion models.
Home-page: 
Author: Shen Zhang, Zhaowei Chen, Zhenyu Zhao, Yuhao Chen, Yao Tang, Jiajun Liang
License-File: LICENSE
